{
  "1": {
    "inputs": {
      "unet_name": "ltx-video-2b-v0.9-Q4_K_S.gguf"
    },
    "class_type": "UnetLoaderGGUF"
  },
  "2": {
    "inputs": {
      "clip_name": "t5xxl_fp8_e4m3fn.safetensors",
      "type": "ltxv"
    },
    "class_type": "CLIPLoader"
  },
  "3": {
    "inputs": {
      "vae_name": "ltx_video_vae.safetensors"
    },
    "class_type": "VAELoader"
  },
  "4": {
    "inputs": {
      "image": "example.png",
      "upload": "image"
    },
    "class_type": "LoadImage"
  },
  "6": {
    "inputs": {
      "text": "low quality, worst quality, deformed, distorted, disfigured, motion smear, motion artifacts, fused fingers, bad anatomy, weird hand, ugly",
      "clip": [
        "2",
        0
      ]
    },
    "class_type": "CLIPTextEncode"
  },
  "22": {
    "inputs": {
      "text": "",
      "clip": [
        "2",
        0
      ]
    },
    "class_type": "CLIPTextEncode"
  },
  "7": {
    "inputs": {
      "positive": [
        "22",
        0
      ],
      "negative": [
        "6",
        0
      ],
      "vae": [
        "3",
        0
      ],
      "image": [
        "4",
        0
      ],
      "width": 768,
      "height": 512,
      "length": 121,
      "batch_size": 1,
      "crf": 29,
      "blur_radius": 0,
      "interpolation": "lanczos",
      "crop": "disabled",
      "strength": 0.9,
      "bypass_i2v": false
    },
    "class_type": "LTXVImgToVideoAdvanced"
  },
  "8": {
    "inputs": {
      "positive": [
        "7",
        0
      ],
      "negative": [
        "7",
        1
      ],
      "frame_rate": 24.0
    },
    "class_type": "LTXVConditioning"
  },
  "9": {
    "inputs": {
      "steps": 8,
      "max_shift": 2.05,
      "base_shift": 0.95,
      "stretch": true,
      "terminal": 0.1,
      "latent": [
        "7",
        2
      ]
    },
    "class_type": "LTXVScheduler"
  },
  "10": {
    "inputs": {
      "sampler_name": "euler"
    },
    "class_type": "KSamplerSelect"
  },
  "11": {
    "inputs": {
      "model": [
        "1",
        0
      ],
      "add_noise": true,
      "noise_seed": 42,
      "cfg": 3.0,
      "positive": [
        "8",
        0
      ],
      "negative": [
        "8",
        1
      ],
      "sampler": [
        "10",
        0
      ],
      "sigmas": [
        "9",
        0
      ],
      "latent_image": [
        "7",
        2
      ]
    },
    "class_type": "SamplerCustom"
  },
  "12": {
    "inputs": {
      "vae": [
        "3",
        0
      ],
      "latents": [
        "11",
        0
      ],
      "spatial_tiles": 4,
      "spatial_overlap": 1,
      "temporal_tile_length": 16,
      "temporal_overlap": 1,
      "last_frame_fix": false,
      "working_device": "auto",
      "working_dtype": "auto"
    },
    "class_type": "LTXVSpatioTemporalTiledVAEDecode"
  },
  "13": {
    "inputs": {
      "images": [
        "12",
        0
      ],
      "frame_rate": 24.0,
      "loop_count": 0,
      "filename_prefix": "ltx_video",
      "format": "video/h264-mp4",
      "pingpong": false,
      "save_output": true
    },
    "class_type": "VHS_VideoCombine"
  }
}